pdf_scrap/__init__.py
pdf_scrap-1.4.dist-info/METADATA
pdf_scrap-1.4.dist-info/WHEEL
pdf_scrap-1.4.dist-info/top_level.txt
pdf_scrap-1.4.dist-info/RECORD
