Metadata-Version: 2.1
Name: pdf_scrap
Version: 1.4
Summary: This package extracts important keywords from a pdf document!!!
Author: Poorvi Prajapati
Requires-Dist: nltk
Requires-Dist: scikit-learn
Requires-Dist: PyPDF2
